pydockexp2/__init__.py
pydockexp2/config/__init__.py
pydockexp2/config/config.py
pydockexp2/config/sample/hard.conf
pydockexp2/config/sample/list.conf
pydockexp2/config/sample/multiple.conf
pydockexp2/config/sample/onfile.conf
pydockexp2/config/sample/simple.conf
pydockexp2/funcs/__init__.py
pydockexp2/funcs/fun.py
pydockexp2/gen.sh
pydockexp2/iterator/__init__.py
pydockexp2/iterator/randgen.py
pydockexp2/main.py
pydockexp2/util/__init__.py
pydockexp2/util/info.json
pydockexp2/util/reader.py
pydockexp2-0.1.0.dist-info/WHEEL
pydockexp2-0.1.0.dist-info/METADATA
pydockexp2-0.1.0.dist-info/RECORD
