Metadata-Version: 2.1
Name: pydockexp2
Version: 0.1.0
Summary: A simple random matrix generato
Home-page: https://github.com/lmriccardo/PyDocker
License: MIT
Author: lmriccardo
Author-email: absintio098@gmail.com
Requires-Python: >=3.9,<4.0
Classifier: License :: OSI Approved :: MIT License
Classifier: Programming Language :: Python :: 3
Classifier: Programming Language :: Python :: 3.9
Requires-Dist: colorama (>=0.4.3,<0.5.0)
Requires-Dist: coloredlogs (>=15.0,<16.0)
Requires-Dist: matplotlib (>=3.4.1,<4.0.0)
Requires-Dist: numpy (>=1.20.2,<2.0.0)
Requires-Dist: pandas (>=1.2.3,<2.0.0)
Requires-Dist: rich (>=10.1.0,<11.0.0)
Requires-Dist: tqdm (>=4.60.0,<5.0.0)
Project-URL: Repository, https://github.com/lmriccardo/PyDocker
